Metadata-Version: 2.1
Name: bootinfo
Version: 0.1.0
Summary: Detect ARM boot signatures on storage devices
Home-page: https://git.sr.ht/~martijnbraam/bootinfo
Author: Martijn Braam
Author-email: martijn@brixit.nl
License: GPL3
Platform: UNKNOWN
License-File: LICENSE
